{
  "version": "7",
  "dialect": "postgresql",
  "entries": [
    {
      "idx": 0,
      "version": "7",
      "when": 1766411547351,
      "tag": "0000_acoustic_celestials",
      "breakpoints": true
    },
    {
      "idx": 1,
      "version": "7",
      "when": 1766459809319,
      "tag": "0001_groovy_hammerhead",
      "breakpoints": true
    },
    {
      "idx": 2,
      "version": "7",
      "when": 1766477517551,
      "tag": "0002_round_ken_ellis",
      "breakpoints": true
    },
    {
      "idx": 3,
      "version": "7",
      "when": 1766490497403,
      "tag": "0003_colorful_obadiah_stane",
      "breakpoints": true
    },
    {
      "idx": 4,
      "version": "7",
      "when": 1766493261187,
      "tag": "0004_clever_madrox",
      "breakpoints": true
    },
    {
      "idx": 5,
      "version": "7",
      "when": 1766627517964,
      "tag": "0005_chief_groot",
      "breakpoints": true
    },
    {
      "idx": 6,
      "version": "7",
      "when": 1766670770120,
      "tag": "0006_workable_ted_forrester",
      "breakpoints": true
    },
    {
      "idx": 7,
      "version": "7",
      "when": 1767147451211,
      "tag": "0007_amazing_stephen_strange",
      "breakpoints": true
    },
    {
      "idx": 8,
      "version": "7",
      "when": 1767318241812,
      "tag": "0008_yielding_taskmaster",
      "breakpoints": true
    }
  ]
}